toshling/__init__.py
toshling/_client.py
toshling/_endpoints.py
toshling/models/__init__.py
toshling/models/argument_types.py
toshling/models/return_types.py
toshling-0.0.4.dist-info/LICENSE
toshling-0.0.4.dist-info/METADATA
toshling-0.0.4.dist-info/WHEEL
toshling-0.0.4.dist-info/top_level.txt
toshling-0.0.4.dist-info/RECORD
