Metadata-Version: 2.1
Name: toshling
Version: 0.0.4
Summary: a Python client library for the Toshl API
Home-page: https://github.com/ioces/toshling
Author: Matthew Schubert
Author-email: ms-toshling@ioces.com
License: MIT License
Platform: UNKNOWN
License-File: LICENSE
Requires-Dist: requests
Requires-Dist: statham-schema
